starforge_library_template/__init__.py
starforge_library_template/__main__.py
starforge_library_template/hello_world.py
starforge_python_library_template-1.0.2.dist-info/licenses/LICENSE
starforge_python_library_template-1.0.2.dist-info/METADATA
starforge_python_library_template-1.0.2.dist-info/WHEEL
starforge_python_library_template-1.0.2.dist-info/entry_points.txt
starforge_python_library_template-1.0.2.dist-info/top_level.txt
starforge_python_library_template-1.0.2.dist-info/RECORD
