Metadata-Version: 2.4
Name: starforge-python-library-template
Version: 1.0.2
Summary: A Python library template for Starforge projects
Author-email: Starforge Worker <star.forge.worker@gmail.com>
Maintainer-email: Starforge Worker <star.forge.worker@gmail.com>
Project-URL: Homepage, https://github.com/starforge-universe/python-library-template
Project-URL: Documentation, https://python-library-template.readthedocs.io/
Project-URL: Repository, https://github.com/starforge-universe/python-library-template
Project-URL: Bug Tracker, https://github.com/starforge-universe/python-library-template/issues
Keywords: template,library,python,starforge
Classifier: Development Status :: 3 - Alpha
Classifier: Intended Audience :: Developers
Classifier: Operating System :: OS Independent
Classifier: Programming Language :: Python :: 3
Classifier: Programming Language :: Python :: 3.10
Classifier: Programming Language :: Python :: 3.11
Classifier: Programming Language :: Python :: 3.12
Classifier: Topic :: Software Development :: Libraries :: Python Modules
Classifier: Topic :: Software Development :: Testing
Requires-Python: >=3.11
License-File: LICENSE
Provides-Extra: dev
Requires-Dist: pylint==3.3.8; extra == "dev"
Requires-Dist: coverage==7.10.7; extra == "dev"
Requires-Dist: sphinx==8.2.3; extra == "dev"
Requires-Dist: sphinx-rtd-theme==3.0.2; extra == "dev"
Requires-Dist: build==1.3.0; extra == "dev"
Requires-Dist: twine==6.2.0; extra == "dev"
Requires-Dist: pytest==8.4.2; extra == "dev"
Requires-Dist: pytest-cov==7.0.0; extra == "dev"
Requires-Dist: pytest-mock==3.15.1; extra == "dev"
Dynamic: license-file
